diadem/conf.py
diadem/version.py
diadem/diadem/diadem.py
diadem/diadem/parametrize.py
diadem/diadem/plot.py
diadem/diadem/visualize.py
diadem/diadem/argbind_strategy/auto.py
diadem/diadem/argbind_strategy/name.py
diadem/diadem/argbind_strategy/pass.py
diadem/diadem/argbind_strategy/ref_match.py
diadem/diadem/argbind_strategy/resource_id.py
diadem/diadem/argbind_strategy/contracts/init.py
diadem/diadem/contracts/init.py
diadem/diadem/match_strategy/clustering.py
diadem/diadem/match_strategy/frequency.py
diadem/diadem/match_strategy/graph.py
diadem/diadem/match_strategy/pass.py
diadem/diadem/match_strategy/reduction.py
diadem/diadem/match_strategy/single.py
diadem/diadem/match_strategy/contracts/init.py
diadem/diadem/param_strategy/attr_concat.py
diadem/diadem/param_strategy/frequency.py
diadem/diadem/param_strategy/graph.py
diadem/diadem/param_strategy/hashing.py
diadem/diadem/param_strategy/index.py
diadem/diadem/param_strategy/readable_hashing.py
diadem/diadem/param_strategy/semantic.py
diadem/diadem/param_strategy/contracts/init.py
diadem-1.0.1.dist-info/LICENSE
diadem-1.0.1.dist-info/METADATA
diadem-1.0.1.dist-info/WHEEL
diadem-1.0.1.dist-info/top_level.txt
diadem-1.0.1.dist-info/RECORD
