Metadata-Version: 2.1
Name: diadem
Version: 1.0.1
Summary: Diadem extends Idem's capabilities, focusing on organizing, parametrizing, and visualizing SLS files across multi-cloud environments.
Home-page: https://gitlab.com/akm0d/diadem
Author: Tyler Levy Conde
Author-email: yonstib@gmail.com
License: Apache Software License 2.0
Classifier: Environment :: Console
Classifier: Intended Audience :: Developers
Classifier: Intended Audience :: Information Technology
Classifier: Intended Audience :: System Administrators
Classifier: Operating System :: OS Independent
Classifier: Programming Language :: Python
Classifier: Programming Language :: Python :: 3.10
Classifier: Programming Language :: Python :: 3.11
Classifier: Development Status :: 5 - Production/Stable
Classifier: License :: OSI Approved :: Apache Software License
Requires-Python: >=3.10
License-File: LICENSE
Requires-Dist: idem
Requires-Dist: networkx
Requires-Dist: pop
Requires-Dist: pop-config >=12.0.1
Provides-Extra: full
Requires-Dist: matplotlib ; extra == 'full'
Requires-Dist: scipy ; extra == 'full'
Provides-Extra: visualize
Requires-Dist: matplotlib ; extra == 'visualize'
Requires-Dist: scipy ; extra == 'visualize'
